arithmetic_expressions/__init__.py
arithmetic_expressions/engine.py
arithmetic_expressions/expression.py
arithmetic_expressions-0.1.dist-info/METADATA
arithmetic_expressions-0.1.dist-info/WHEEL
arithmetic_expressions-0.1.dist-info/RECORD
